{"count": 23, "result": 0, "v": 0, "items": [{"updated": "2013-01-31", "price": 12.0, "new_price": 6.0, "expire": 32503647600.0, "authors": "张向东\n林郁", "score_count": 0, "title": "创业者对话创业者", "paper_price": 29.0, "cover": "http://c.duokan.com/cover/2013/01/e4cbe4391afe6958.jpg!s", "editors": "", "summary": "探讨商业和创造的价值，寻找勇气和智慧的源头", "comment_count": 0, "score": 0.0, "book_id": "91b7221c6b9211e2808800163e0123ac", "sid": 20772}, {"updated": "2013-01-31", "price": 12.0, "new_price": 6.0, "expire": 32503647600.0, "authors": "韩松", "score_count": 0, "title": "地铁", "paper_price": 29.0, "cover": "http://c.duokan.com/cover/2013/01/e1e4c36d337cd61c.jpg!s", "editors": "", "summary": "其实最真实的，你永远料想不到！", "comment_count": 1, "score": 0.0, "book_id": "a698a3d26a0111e299d100163e0123ac", "sid": 20357}, {"updated": "2013-01-22", "price": 12.0, "new_price": 6.0, "expire": 32503647600.0, "authors": "", "score_count": 0, "title": "开放中国：改革的30年记忆", "paper_price": 42.0, "cover": "http://c.duokan.com/cover/2012/11/7dad22d8c6743faa.jpg!s", "editors": "经济观察报", "summary": "30年30段巨细混杂的记忆，探寻表象下的变革力量", "comment_count": 0, "score": 0.0, "book_id": "959028083ad611e297e200163e0123ac", "sid": 14997}, {"updated": "2013-01-22", "price": 18.0, "new_price": 12.0, "expire": 32503647600.0, "authors": "宋守山", "score_count": 0, "title": "《资治通鉴》管理日志", "paper_price": 39.0, "cover": "http://c.duokan.com/cover/2012/11/02b3b21ec0975945.jpg!s", "editors": "", "summary": "以国学智慧通透管理，以管理思维重读国学", "comment_count": 0, "score": 0.0, "book_id": "292488b23adb11e297e200163e0123ac", "sid": 15177}, {"updated": "2013-01-22", "price": 18.0, "new_price": 12.0, "expire": 32503647600.0, "authors": "何志毅", "score_count": 0, "title": "北大案例经典", "paper_price": 45.0, "cover": "http://c.duokan.com/cover/2012/11/f85b85c08e1b43cc.jpg!s", "editors": "", "summary": "精选中国企业经典案例，网聚企管专家权威点评。", "comment_count": 0, "score": 0.0, "book_id": "1752ceb43adb11e297e200163e0123ac", "sid": 15172}, {"updated": "2013-01-29", "price": 18.0, "new_price": 12.0, "expire": 32503647600.0, "authors": "宝树", "score_count": 0, "title": "古老的地球之歌", "paper_price": 28.0, "cover": "http://c.duokan.com/cover/2013/01/994782122c1fcdf7.jpg!s", "editors": "", "summary": "一本最能代表国内科幻界较高原创水平的短篇小说集！", "comment_count": 0, "score": 0.0, "book_id": "2a257ce2661111e2bee100163e0123ac", "sid": 19582}, {"updated": "2013-01-29", "price": 12.0, "new_price": 6.0, "expire": 32503647600.0, "authors": "", "score_count": 0, "title": "记者不写新闻", "paper_price": 28.0, "cover": "http://c.duokan.com/cover/2012/11/45f23f18dc787085.jpg!s", "editors": "陈文定", "summary": "记者们不饰伪的展露他们内心的迷茫、失落与挣扎。", "comment_count": 0, "score": 0.0, "book_id": "c3c2b774321e11e28a9300163e0123ac", "sid": 12242}, {"updated": "2013-02-22", "price": 25.0, "new_price": 18.0, "expire": 32503647600.0, "authors": "唐立淇", "score_count": 0, "title": "唐立淇2013星座运程", "paper_price": 49.9, "cover": "http://c.duokan.com/cover/2013/01/3844abd3c69b48c5.jpg!s", "editors": "", "summary": "亚洲最强占星专家，年度运势书第一品牌，准到骨子里！", "comment_count": 0, "score": 0.0, "book_id": "66fff13e6a0211e299d100163e0123ac", "sid": 20387}, {"updated": "2013-01-29", "price": 18.0, "new_price": 12.0, "expire": 32503647600.0, "authors": "【美】查尔斯·埃利斯", "score_count": 0, "title": "高盛帝国（上）", "paper_price": 42.0, "cover": "http://c.duokan.com/cover/2013/01/edac5126f475b01a.jpg!s", "editors": "", "summary": "全球唯一一部全面讲述高盛屹立百年的企业传记", "comment_count": 0, "score": 0.0, "book_id": "14ff5e6c661811e2bee100163e0123ac", "sid": 19727}, {"updated": "2013-02-05", "price": 18.0, "new_price": 6.0, "expire": 32503647600.0, "authors": "喜宏", "score_count": 9, "title": "春晚", "paper_price": 29.0, "cover": "http://c.duokan.com/cover/2013/01/cf45b73151f311d7.jpg!s", "editors": "", "summary": "电视界策划大腕独家披露“春晚“幕后，并非纪实却绝对透彻！", "comment_count": 3, "score": 4.2, "book_id": "279a4cca6a0111e299d100163e0123ac", "sid": 20352}, {"updated": "2013-01-29", "price": 12.0, "new_price": 6.0, "expire": 32503647600.0, "authors": "叶圣陶", "score_count": 0, "title": "大家国学：叶圣陶", "paper_price": 35.0, "cover": "http://c.duokan.com/cover/2013/01/bff69a49fadb9c42.jpg!s", "editors": "", "summary": "前辈大师的国学修为，今日大众的国学养分也。", "comment_count": 0, "score": 0.0, "book_id": "f483005c322911e28a9300163e0123ac", "sid": 12622}, {"updated": "2013-01-29", "price": 12.0, "new_price": 6.0, "expire": 32503647600.0, "authors": "张鸣", "score_count": 0, "title": "中国教育病了吗?", "paper_price": 35.0, "cover": "http://c.duokan.com/cover/2012/11/b1fbbb5331225315.jpg!s", "editors": "", "summary": "易中天、陈丹青、梁文道、吴思、龙应台强力推荐！", "comment_count": 0, "score": 0.0, "book_id": "c0665d7c322011e28a9300163e0123ac", "sid": 12287}, {"updated": "2013-01-24", "price": 25.0, "new_price": 18.0, "expire": 32503647600.0, "authors": "【英】Ben Frain", "score_count": 0, "title": "响应式Web设计：HTML5和CSS3实战", "paper_price": 49.0, "cover": "http://c.duokan.com/cover/2013/01/73c8384a793c3118.jpg!s", "editors": "", "summary": "网站运营必备利器；未来处于技术主流地位的响应式设计", "comment_count": 1, "score": 0.0, "book_id": "fb3d92a2660611e2bee100163e0123ac", "sid": 19517}, {"updated": "2013-01-22", "price": 18.0, "new_price": 12.0, "expire": 32503647600.0, "authors": "金错刀", "score_count": 0, "title": "史蒂夫·乔布斯管理日志", "paper_price": 42.0, "cover": "http://c.duokan.com/cover/2012/11/8d79c0ab03bbed84.jpg!s", "editors": "", "summary": "展现乔布斯“天使”与“恶魔”双重性格下的管理思想", "comment_count": 0, "score": 0.0, "book_id": "9912a6a23ad811e297e200163e0123ac", "sid": 15082}, {"updated": "2013-01-22", "price": 12.0, "new_price": 6.0, "expire": 32503647600.0, "authors": "唐凯林", "score_count": 0, "title": "走，到二线城市去", "paper_price": 32.0, "cover": "http://c.duokan.com/cover/2012/11/bbb5957ee5a2d055.jpg!s", "editors": "", "summary": "一线的挣扎or二线的激情，直击都市白领的内心", "comment_count": 1, "score": 0.0, "book_id": "aa3819083ad811e297e200163e0123ac", "sid": 15087}, {"updated": "2013-01-28", "price": 18.0, "new_price": 12.0, "expire": 32503647600.0, "authors": "宋建文", "score_count": 0, "title": "K线其实很简单", "paper_price": 49.8, "cover": "http://c.duokan.com/cover/2013/01/a842993fac3a648b.jpg!s", "editors": "", "summary": "从零开始，由浅入深，详细分析60种K线形态。", "comment_count": 0, "score": 0.0, "book_id": "c5a650723ada11e297e200163e0123ac", "sid": 15152}, {"updated": "2013-01-17", "price": 18.0, "new_price": 12.0, "expire": 32503647600.0, "authors": "毛翔", "score_count": 0, "title": "嗜血的老狐狸司马懿", "paper_price": 29.8, "cover": "http://c.duokan.com/cover/2013/01/4fc4affb5f5ff47a.jpg!s", "editors": "", "summary": "隐忍数十年，老狐狸司马懿一口口吃掉三国的嗜血历程", "comment_count": 0, "score": 0.0, "book_id": "44b3defa607b11e2957400163e0123ac", "sid": 18482}, {"updated": "2013-01-29", "price": 12.0, "new_price": 6.0, "expire": 32503647600.0, "authors": "金大中", "score_count": 0, "title": "金大中自述", "paper_price": 49.8, "cover": "http://c.duokan.com/cover/2012/11/0d5982d380370ff7.jpg!s", "editors": "", "summary": "为了民主，我不后悔！", "comment_count": 0, "score": 0.0, "book_id": "955cd1c8322111e28a9300163e0123ac", "sid": 12312}, {"updated": "2013-01-24", "price": 18.0, "new_price": 12.0, "expire": 32503647600.0, "authors": "吴晓波", "score_count": 18, "title": "激荡三十年（上） ", "paper_price": 77.0, "cover": "http://c.duokan.com/cover/2012/11/49b9dd4ee9e6258a.jpg!s", "editors": "", "summary": "资本苏醒的年代，一个不浪漫的商业春天", "comment_count": 8, "score": 8.6, "book_id": "050bc61e3add11e297e200163e0123ac", "sid": 15292}, {"updated": "2013-01-24", "price": 12.0, "new_price": 6.0, "expire": 32503647600.0, "authors": "指纹", "score_count": 5, "title": "刀锋上的救赎", "paper_price": 29.8, "cover": "http://c.duokan.com/cover/2013/01/9df8c231000b2681.jpg!s", "editors": "", "summary": "最具质感的国产冷硬派犯罪小说，张绍刚、撒贝宁推荐。", "comment_count": 0, "score": 7.6, "book_id": "df118c36394311e29ad000163e0123ac", "sid": 14297}, {"updated": "2013-01-22", "price": 18.0, "new_price": 12.0, "expire": 32503647600.0, "authors": "尹生", "score_count": 0, "title": "逆流而上", "paper_price": 37.0, "cover": "http://c.duokan.com/cover/2012/11/7f953c51cd7b9a7a.jpg!s", "editors": "", "summary": "中国百家标杆企业系列之中兴篇", "comment_count": 0, "score": 0.0, "book_id": "17a551ea3ad911e297e200163e0123ac", "sid": 15112}, {"updated": "2013-01-25", "price": 25.0, "new_price": 18.0, "expire": 32503647600.0, "authors": "任进", "score_count": 0, "title": "无设计不奢侈", "paper_price": 58.0, "cover": "http://c.duokan.com/cover/2012/11/6a7d9abb838b7567.jpg!s", "editors": "", "summary": "越王珠宝首席设计师任进，讲述珠宝设计背后的故事。", "comment_count": 0, "score": 0.0, "book_id": "11b98c623adc11e297e200163e0123ac", "sid": 15232}, {"updated": "2013-01-24", "price": 12.0, "new_price": 6.0, "expire": 32503647600.0, "authors": "王旭明", "score_count": 0, "title": "明正言顺：王旭明谈官员的说话之道", "paper_price": 29.8, "cover": "http://c.duokan.com/cover/2012/11/ca1631533fb9cdd2.jpg!s", "editors": "", "summary": "开启官智，教官员学说话的入门读物", "comment_count": 0, "score": 0.0, "book_id": "1c0ed158323111e28a9300163e0123ac", "sid": 12767}], "total": 0, "more": true}